explain_ok/__init__.py
explain_ok/api.py
explain_ok/context.py
explain_ok/exceptions.py
explain_ok/nodes.py
explain_ok/serializer.py
explain_ok/tracer.py
explain_ok-0.1.1.dist-info/METADATA
explain_ok-0.1.1.dist-info/WHEEL
explain_ok-0.1.1.dist-info/licenses/LICENSE
explain_ok-0.1.1.dist-info/RECORD
