Metadata-Version: 2.4
Name: explain-ok
Version: 0.1.1
Summary: Calculation-level explainability for Python computations
Project-URL: Homepage, https://github.com/Omkar3344/explain-ok
Project-URL: Documentation, https://github.com/Omkar3344/explain-ok/blob/main/README.md
Project-URL: Repository, https://github.com/Omkar3344/explain-ok
Author-email: Omkar Kadam <omkarkadam170604@gmail.com>
License-Expression: MIT
License-File: LICENSE
Keywords: computation,debugging,explainability,interpretability,tracing
Classifier: Development Status :: 3 - Alpha
Classifier: Intended Audience :: Developers
Classifier: Intended Audience :: Science/Research
Classifier: License :: OSI Approved :: MIT License
Classifier: Operating System :: OS Independent
Classifier: Programming Language :: Python :: 3
Classifier: Programming Language :: Python :: 3.9
Classifier: Programming Language :: Python :: 3.10
Classifier: Programming Language :: Python :: 3.11
Classifier: Programming Language :: Python :: 3.12
Classifier: Programming Language :: Python :: 3.13
Classifier: Topic :: Scientific/Engineering
Classifier: Topic :: Software Development :: Debuggers
Classifier: Typing :: Typed
Requires-Python: >=3.9
Provides-Extra: dev
Requires-Dist: pytest-cov>=4.0; extra == 'dev'
Requires-Dist: pytest>=7.0; extra == 'dev'
